<?xml version="1.0" encoding="utf-8" ?>
<dwsync>
<file name="header.php" local="130603271670000000" remote="130603271670000000" testing="130603271670000000" />
<file name="test_action.php" local="130603271700000000" remote="130603271700000000" testing="130603271700000000" />
<file name="index_ideal.php" local="130603271680000000" remote="130603271680000000" testing="130603271680000000" />
<file name="index_beta.php" local="130603271680000000" remote="130603271680000000" testing="130603271680000000" />
<file name="action_page_template_creator-2.php" local="130603271650000000" remote="130603271650000000" testing="130603271650000000" />
<file name="README.md" local="130603271700000000" remote="130603271700000000" testing="130603271700000000" />
<file name="action_edit_form_creator_original.php" local="130603271640000000" remote="130603271640000000" testing="130603271640000000" />
<file name="package.json" local="130603271690000000" remote="130603271690000000" testing="130603271690000000" />
<file name="action_list_creator_original.php" local="130603271650000000" remote="130603271650000000" testing="130603271650000000" />
<file name="action_class_creator_orginal.php" local="130603271640000000" remote="130603271640000000" testing="130603271640000000" />
<file name="action_page_template_creator.php" local="130603271660000000" remote="130603271660000000" testing="130603271660000000" />
<file name="test_json.php" local="130603271710000000" remote="130603271710000000" testing="130603271710000000" />
<file name="ajax.php" local="130603271670000000" remote="130603271670000000" testing="130603271670000000" />
<file name="action_page_template_creator_original.php" local="130603271660000000" remote="130603271660000000" testing="130603271660000000" />
<file name="index_old.php" local="130603271690000000" remote="130603271690000000" testing="130603271690000000" />
</dwsync>